Classfile /Users/liyu/Workspace/Git/Learn/Java/src/sdk/Test4.class
  Last modified 2017年10月10日; size 1151 bytes
  MD5 checksum 99a6f828469daab763ca85ee7fd2526f
  Compiled from "Test4.java"
public class sdk.Test4
  minor version: 0
  major version: 53
  flags: (0x0021) ACC_PUBLIC, ACC_SUPER
  this_class: #5                          // sdk/Test4
  super_class: #9                         // java/lang/Object
  interfaces: 0, fields: 0, methods: 4, attributes: 3
Constant pool:
   #1 = Methodref          #9.#21         // java/lang/Object."<init>":()V
   #2 = Fieldref           #22.#23        // java/lang/System.out:Ljava/io/PrintStream;
   #3 = InvokeDynamic      #0:#27         // #0:makeConcatWithConstants:(I)Ljava/lang/String;
   #4 = Methodref          #28.#29        // java/io/PrintStream.println:(Ljava/lang/String;)V
   #5 = Class              #30            // sdk/Test4
   #6 = Methodref          #5.#21         // sdk/Test4."<init>":()V
   #7 = Methodref          #5.#31         // sdk/Test4.add_100_for:()V
   #8 = Methodref          #5.#32         // sdk/Test4.add_100_while:()V
   #9 = Class              #33            // java/lang/Object
  #10 = Utf8               <init>
  #11 = Utf8               ()V
  #12 = Utf8               Code
  #13 = Utf8               LineNumberTable
  #14 = Utf8               add_100_while
  #15 = Utf8               StackMapTable
  #16 = Utf8               add_100_for
  #17 = Utf8               main
  #18 = Utf8               ([Ljava/lang/String;)V
  #19 = Utf8               SourceFile
  #20 = Utf8               Test4.java
  #21 = NameAndType        #10:#11        // "<init>":()V
  #22 = Class              #34            // java/lang/System
  #23 = NameAndType        #35:#36        // out:Ljava/io/PrintStream;
  #24 = Utf8               BootstrapMethods
  #25 = MethodHandle       6:#37          // REF_invokeStatic java/lang/invoke/StringConcatFactory.makeConcatWithConstants:(Ljava/lang/invoke/MethodHandles$Lookup;Ljava/lang/String;Ljava/lang/invoke/MethodType;Ljava/lang/String;[Ljava/lang/Object;)Ljava/lang/invoke/CallSite;
  #26 = String             #38            // 1 + ... + 100 = \u0001
  #27 = NameAndType        #39:#40        // makeConcatWithConstants:(I)Ljava/lang/String;
  #28 = Class              #41            // java/io/PrintStream
  #29 = NameAndType        #42:#43        // println:(Ljava/lang/String;)V
  #30 = Utf8               sdk/Test4
  #31 = NameAndType        #16:#11        // add_100_for:()V
  #32 = NameAndType        #14:#11        // add_100_while:()V
  #33 = Utf8               java/lang/Object
  #34 = Utf8               java/lang/System
  #35 = Utf8               out
  #36 = Utf8               Ljava/io/PrintStream;
  #37 = Methodref          #44.#45        // java/lang/invoke/StringConcatFactory.makeConcatWithConstants:(Ljava/lang/invoke/MethodHandles$Lookup;Ljava/lang/String;Ljava/lang/invoke/MethodType;Ljava/lang/String;[Ljava/lang/Object;)Ljava/lang/invoke/CallSite;
  #38 = Utf8               1 + ... + 100 = \u0001
  #39 = Utf8               makeConcatWithConstants
  #40 = Utf8               (I)Ljava/lang/String;
  #41 = Utf8               java/io/PrintStream
  #42 = Utf8               println
  #43 = Utf8               (Ljava/lang/String;)V
  #44 = Class              #46            // java/lang/invoke/StringConcatFactory
  #45 = NameAndType        #39:#50        // makeConcatWithConstants:(Ljava/lang/invoke/MethodHandles$Lookup;Ljava/lang/String;Ljava/lang/invoke/MethodType;Ljava/lang/String;[Ljava/lang/Object;)Ljava/lang/invoke/CallSite;
  #46 = Utf8               java/lang/invoke/StringConcatFactory
  #47 = Class              #52            // java/lang/invoke/MethodHandles$Lookup
  #48 = Utf8               Lookup
  #49 = Utf8               InnerClasses
  #50 = Utf8               (Ljava/lang/invoke/MethodHandles$Lookup;Ljava/lang/String;Ljava/lang/invoke/MethodType;Ljava/lang/String;[Ljava/lang/Object;)Ljava/lang/invoke/CallSite;
  #51 = Class              #53            // java/lang/invoke/MethodHandles
  #52 = Utf8               java/lang/invoke/MethodHandles$Lookup
  #53 = Utf8               java/lang/invoke/MethodHandles
{
  public sdk.Test4();
    descriptor: ()V
    flags: (0x0001) ACC_PUBLIC
    Code:
      stack=1, locals=1, args_size=1
         0: aload_0
         1: invokespecial #1                  // Method java/lang/Object."<init>":()V
         4: return
      LineNumberTable:
        line 12: 0

  protected void add_100_while();
    descriptor: ()V
    flags: (0x0004) ACC_PROTECTED
    Code:
      stack=2, locals=3, args_size=1
         0: iconst_0
         1: istore_1
         2: iconst_1
         3: istore_2
         4: iload_2
         5: bipush        100
         7: if_icmpgt     20
        10: iload_1
        11: iload_2
        12: iadd
        13: istore_1
        14: iinc          2, 1
        17: goto          4
        20: getstatic     #2                  // Field java/lang/System.out:Ljava/io/PrintStream;
        23: iload_1
        24: invokedynamic #3,  0              // InvokeDynamic #0:makeConcatWithConstants:(I)Ljava/lang/String;
        29: invokevirtual #4                  // Method java/io/PrintStream.println:(Ljava/lang/String;)V
        32: return
      LineNumberTable:
        line 15: 0
        line 16: 2
        line 17: 4
        line 18: 10
        line 19: 14
        line 21: 20
        line 22: 32
      StackMapTable: number_of_entries = 2
        frame_type = 253 /* append */
          offset_delta = 4
          locals = [ int, int ]
        frame_type = 15 /* same */

  void add_100_for();
    descriptor: ()V
    flags: (0x0000)
    Code:
      stack=2, locals=3, args_size=1
         0: iconst_0
         1: istore_1
         2: iconst_1
         3: istore_2
         4: iload_2
         5: bipush        100
         7: if_icmpgt     20
        10: iload_1
        11: iload_2
        12: iadd
        13: istore_1
        14: iinc          2, 1
        17: goto          4
        20: getstatic     #2                  // Field java/lang/System.out:Ljava/io/PrintStream;
        23: iload_1
        24: invokedynamic #3,  0              // InvokeDynamic #0:makeConcatWithConstants:(I)Ljava/lang/String;
        29: invokevirtual #4                  // Method java/io/PrintStream.println:(Ljava/lang/String;)V
        32: return
      LineNumberTable:
        line 25: 0
        line 26: 2
        line 27: 10
        line 26: 14
        line 29: 20
        line 30: 32
      StackMapTable: number_of_entries = 2
        frame_type = 253 /* append */
          offset_delta = 4
          locals = [ int, int ]
        frame_type = 250 /* chop */
          offset_delta = 15

  public static void main(java.lang.String[]);
    descriptor: ([Ljava/lang/String;)V
    flags: (0x0009) ACC_PUBLIC, ACC_STATIC
    Code:
      stack=2, locals=2, args_size=1
         0: new           #5                  // class sdk/Test4
         3: dup
         4: invokespecial #6                  // Method "<init>":()V
         7: astore_1
         8: aload_1
         9: invokevirtual #7                  // Method add_100_for:()V
        12: aload_1
        13: invokevirtual #8                  // Method add_100_while:()V
        16: return
      LineNumberTable:
        line 33: 0
        line 34: 8
        line 35: 12
        line 36: 16
}
SourceFile: "Test4.java"
InnerClasses:
  public static final #48= #47 of #51;    // Lookup=class java/lang/invoke/MethodHandles$Lookup of class java/lang/invoke/MethodHandles
BootstrapMethods:
  0: #25 REF_invokeStatic java/lang/invoke/StringConcatFactory.makeConcatWithConstants:(Ljava/lang/invoke/MethodHandles$Lookup;Ljava/lang/String;Ljava/lang/invoke/MethodType;Ljava/lang/String;[Ljava/lang/Object;)Ljava/lang/invoke/CallSite;
    Method arguments:
      #26 1 + ... + 100 = \u0001
